[
  {
    "type": "navbar",
    "name": "navbar",
    "category": "navbar",
    "brand": {
      "text": "Your Brand"
    },
    "navLinks": [
      {
        "text": "Home"
      },
      {
        "text": "About"
      },
      {
        "text": "Jobs"
      },
      {
        "text": "Contacts"
      },
      {
        "text": "Products"
      }
    ],
    "bgColor": {
      "r": 150,
      "g": 150,
      "b": 150,
      "a": 1
    }
  },
  {
    "type": "body",
    "htmlTag": "div",
    "name": "hero-with-image",
    "category": "hero",
    "items": [
      {
        "image": {
          "src": "/books.jpg",
          "style": {
            "width": "700",
            "height": "500"
          }
        },
        "content": {
          "title": "Responsive left-aligned hero with image",
          "subtitle": "Quickly design and customize responsive mobile-first sites with Bootstrap, the world's most popular front-end open source toolkit, featuring Sass variables and mixins, responsive grid system, extensive prebuilt components, and powerful JavaScript plugins.",
          "primaryButton": {
            "text": "Primary",
            "variant": "primary"
          },
          "secondaryButton": {
            "text": "Secondary",
            "variant": "outline-secondary"
          }
        }
      }
    ],
    "style": {
      "display": "flex",
      "alignItems": "center",
      "justifyContent": "space-around",
      "width": "100",
      "height": "600",
      "padding": {
        "top": 0,
        "right": 0,
        "bottom": 0,
        "left": 0
      },
      "backgroundColor": "#a84d4d",
      "backgroundImage": "/landing.jpg"
    }
  },
  {
    "type": "body",
    "htmlTag": "button",
    "name": "button",
    "category": "content",
    "text": "Click Me",
    "style": {
      "backgroundColor": "#008CBA",
      "color": "#fff",
      "padding": {
        "top": 10,
        "right": 20,
        "bottom": 10,
        "left": 20
      },
      "borderRadius": "5px"
    }
  },
  {
    "type": "body",
    "name": "main-content",

    "bgColor": {
      "r": 240,
      "g": 240,
      "b": 240,
      "a": 1
    }
  },
  {
    "type": "body",
    "htmlTag": "img",
    "name": "image",
    "category": "content",
    "src": "/books.jpg",
    "alt": "Example Image",
    "style": {
      "width": 500,
      "height": 300,
      "borderRadius": "10px"
    }
  },
  {
    "type": "body",
    "htmlTag": "p",
    "name": "paragraph",
    "category": "content",
    "text": "Lorem ipsum dolor sit amet, consectetur adipiscing elit.",
    "style": {
      "color": "#000",
      "fontSize": "1.2em",
      "fontWeight": "normal"
    }
  },
  {
    "type": "body",
    "name": "testimonials",

    "bgColor": {
      "r": 210,
      "g": 210,
      "b": 210,
      "a": 1
    }
  },
  {
    "type": "body",
    "name": "pricing",
    "category": "pricing",
    "items": [
      {
        "title": {
          "text": "Pricing"
        },
        "subtitle": {
          "text": "Quickly build an effective pricing table for your potential customers with this Bootstrap example. It's built with default Bootstrap components and utilities with little customization."
        },
        "cards": [
          {
            "header": {
              "text": "Free"
            },
            "body": {
              "price": {
                "currency": "$",
                "value": "0",
                "paymentFrequency": "/mo"
              },
              "listedItems": [
                {
                  "text": "10 users included"
                },
                {
                  "text": "2 GB of storage"
                },
                {
                  "text": "Email support"
                },
                {
                  "text": "Help center access"
                }
              ],
              "button": {
                "text": "Sign up for free",
                "href": "#",
                "variant": "outline-primary"
              }
            }
          },
          {
            "header": {
              "text": "Pro"
            },
            "body": {
              "price": {
                "currency": "$",
                "value": "15",
                "paymentFrequency": "/mo"
              },
              "listedItems": [
                {
                  "text": "20 users included"
                },
                {
                  "text": "10 GB of storage"
                },
                {
                  "text": "Priority Email support"
                },
                {
                  "text": "Help center access"
                }
              ],
              "button": {
                "text": "Get started",
                "href": "#",
                "variant": "primary"
              }
            }
          },
          {
            "header": {
              "text": "Enterprise"
            },
            "body": {
              "price": {
                "currency": "$",
                "value": "29",
                "paymentFrequency": "/mo"
              },
              "listedItems": [
                {
                  "text": "30 users included"
                },
                {
                  "text": "15 GB of storage"
                },
                {
                  "text": "Phone and email support"
                },
                {
                  "text": "Help center access"
                }
              ],
              "button": {
                "text": "Contact us",
                "href": "#",
                "variant": "primary"
              }
            }
          }
        ]
      }
    ],

    "bgColor": {
      "r": 200,
      "g": 200,
      "b": 200,
      "a": 1
    }
  },
  {
    "type": "footer",
    "name": "footer",
    "items": [
      {
        "header": {
          "text": "Section 1"
        },
        "links": [
          {
            "text": "Home",
            "href": "#"
          },
          {
            "text": "Features",
            "href": "#"
          },
          {
            "text": "Pricing",
            "href": "#"
          },
          {
            "text": "FAQs",
            "href": "#"
          },
          {
            "text": "About",
            "href": "#"
          }
        ]
      },
      {
        "header": {
          "text": "Section 2"
        },
        "links": [
          {
            "text": "Home",
            "href": "#"
          },
          {
            "text": "Features",
            "href": "#"
          },
          {
            "text": "Pricing",
            "href": "#"
          },
          {
            "text": "FAQs",
            "href": "#"
          },
          {
            "text": "About",
            "href": "#"
          }
        ]
      },
      {
        "header": {
          "text": "Section 3"
        },
        "links": [
          {
            "text": "Home",
            "href": "#"
          },
          {
            "text": "Features",
            "href": "#"
          },
          {
            "text": "Pricing",
            "href": "#"
          },
          {
            "text": "FAQs",
            "href": "#"
          },
          {
            "text": "About",
            "href": "#"
          }
        ]
      }
    ],

    "bgColor": {
      "r": 150,
      "g": 150,
      "b": 150,
      "a": 1
    }
  },
  {
    "type": "body",
    "name": "blog",
    "category": "blog",
    "items": [
      {
        "title": {
          "text": "Featured Posts"
        },
        "cards": [
          {
            "header": {
              "text": "Title of a longer featured blog post"
            },
            "body": {
              "text": "Multiple lines of text that form the lede, informing new readers quickly and efficiently about what’s most interesting in this post’s contents.",
              "link": {
                "text": "Continue reading...",
                "href": "#"
              },
              "bgColor": {
                "r": 0,
                "g": 0,
                "b": 0,
                "a": 1
              },
              "textColor": {
                "r": 255,
                "g": 255,
                "b": 255,
                "a": 1
              }
            },
            "image": {
              "src": "https://via.placeholder.com/200x250?text=Thumbnail",
              "alt": "Thumbnail"
            },
            "categoryTag": {
              "text": "World",
              "bgColor": {
                "r": 0,
                "g": 123,
                "b": 255,
                "a": 1
              },
              "textColor": {
                "r": 255,
                "g": 255,
                "b": 255,
                "a": 1
              }
            }
          },
          {
            "header": {
              "text": "Post title"
            },
            "body": {
              "text": "This is a wider card with supporting text below as a natural lead-in to additional content.",
              "link": {
                "text": "Continue reading...",
                "href": "#"
              },
              "bgColor": {
                "r": 255,
                "g": 255,
                "b": 255,
                "a": 1
              },
              "textColor": {
                "r": 0,
                "g": 0,
                "b": 0,
                "a": 1
              }
            },
            "image": {
              "src": "https://via.placeholder.com/200x250?text=Thumbnail",
              "alt": "Thumbnail"
            },
            "categoryTag": {
              "text": "Design",
              "bgColor": {
                "r": 40,
                "g": 167,
                "b": 69,
                "a": 1
              },
              "textColor": {
                "r": 255,
                "g": 255,
                "b": 255,
                "a": 1
              }
            }
          }
        ]
      }
    ]
  },
  {
    "type": "body",
    "name": "featuresA",
    "category": "featuresA",
    "items": [
      {
        "title": {
          "text": "Features examples"
        },
        "sections": [
          {
            "title": {
              "text": "Columns with icons"
            },
            "icon": {
              "name": "collection",
              "size": "1em"
            },
            "cards": [
              {
                "title": {
                  "text": "Featured title"
                },
                "description": {
                  "text": "Paragraph of text beneath the heading to explain the heading. We'll add onto it with another sentence and probably just keep going until we run out of words."
                },
                "button": {
                  "text": "Call to action",
                  "href": "#",
                  "icon": "chevron-right"
                }
              },
              {
                "title": {
                  "text": "Featured title 2"
                },
                "description": {
                  "text": "Paragraph of text beneath the heading to explain the heading. We'll add onto it with another sentence and probably just keep going until we run out of words."
                },
                "button": {
                  "text": "Call to action 2",
                  "href": "#",
                  "icon": "chevron-right"
                }
              },
              {
                "title": {
                  "text": "Featured title 3"
                },
                "description": {
                  "text": "Paragraph of text beneath the heading to explain the heading. We'll add onto it with another sentence and probably just keep going until we run out of words."
                },
                "button": {
                  "text": "Call to action 3",
                  "href": "#",
                  "icon": "chevron-right"
                }
              }
            ]
          }
        ]
      }
    ],

    "bgColor": {
      "r": 200,
      "g": 200,
      "b": 200,
      "a": 1
    }
  },
  {
    "type": "body",
    "name": "featuresB",
    "category": "featuresB",
    "items": [
      {
        "title": {
          "text": "Left-aligned title explaining these awesome features"
        },
        "sections": [
          {
            "icon": {
              "name": "collection",
              "size": "1em"
            },
            "cards": [
              {
                "title": {
                  "text": "Featured title"
                },
                "description": {
                  "text": "Paragraph of text beneath the heading to explain the heading."
                }
              },
              {
                "title": {
                  "text": "Featured title"
                },
                "description": {
                  "text": "Paragraph of text beneath the heading to explain the heading."
                }
              },
              {
                "title": {
                  "text": "Featured title"
                },
                "description": {
                  "text": "Paragraph of text beneath the heading to explain the heading."
                }
              },
              {
                "title": {
                  "text": "Featured title"
                },
                "description": {
                  "text": "Paragraph of text beneath the heading to explain the heading."
                }
              }
            ]
          }
        ]
      }
    ],

    "bgColor": {
      "r": 200,
      "g": 200,
      "b": 200,
      "a": 1
    }
  },
  {
    "type": "body",
    "name": "imageRight",
    "category": "imageRight",
    "items": [
      {
        "title": {
          "text": "Columns with images"
        },
        "icon": {
          "name": "image",
          "size": "1em"
        },
        "cards": [
          {
            "title": {
              "text": "First featurette heading."
            },
            "description": {
              "text": "Some great placeholder content for the first featurette here. Imagine some exciting prose here."
            },
            "image": {
              "src": "https://via.placeholder.com/500x500",
              "alt": "Placeholder: 500x500"
            }
          }
        ]
      }
    ],

    "bgColor": {
      "r": 200,
      "g": 200,
      "b": 200,
      "a": 1
    }
  },
  {
    "type": "body",
    "name": "imageLeft",
    "category": "imageLeft",
    "items": [
      {
        "title": {
          "text": "Oh yeah, it's that good. See for yourself."
        },
        "cards": [
          {
            "title": {
              "text": "Another featurette?"
            },
            "description": {
              "text": "Of course. More placeholder content here to give you an idea of how this layout would work with some actual real-world content in place."
            },
            "image": {
              "src": "https://via.placeholder.com/500x500",
              "alt": "Placeholder: 500x500"
            }
          }
        ]
      }
    ],

    "bgColor": {
      "r": 255,
      "g": 255,
      "b": 255,
      "a": 1
    }
  }
]
